setup.cfg
setup.py
pyvizio_speaker/__init__.py
pyvizio_speaker/api_command.py
pyvizio_speaker/api_response.py
pyvizio_speaker/util.py
pyvizio_speaker.egg-info/PKG-INFO
pyvizio_speaker.egg-info/SOURCES.txt
pyvizio_speaker.egg-info/dependency_links.txt
pyvizio_speaker.egg-info/requires.txt
pyvizio_speaker.egg-info/top_level.txt