Metadata-Version: 1.1
Name: pyvizio-speaker
Version: 0.0.1
Summary: Python library for controlling Vizio SmartCast Speakers
Home-page: https://github.com/jeradM/pyvizio_speaker
Author: Jerad Meisner
Author-email: jerad.meisner@gmail.com
License: UNKNOWN
Download-URL: https://github.com/jeradM/pyvizio_speaker/archive/0.0.1.tar.gz
Keywords: Vizio,SmartCast,Soundbar,Speaker
Platform: UNKNOWN
